barchart_api/__init__.py
barchart_api/barchart_api.py
barchart_api/decorators.py
barchart_api/exceptions.py
barchart_api/version.py
barchart_api-0.12.4.dist-info/LICENSE
barchart_api-0.12.4.dist-info/METADATA
barchart_api-0.12.4.dist-info/WHEEL
barchart_api-0.12.4.dist-info/top_level.txt
barchart_api-0.12.4.dist-info/RECORD
